{"_type":"export","__export_format":4,"__export_date":"2019-10-14T18:32:41.497Z","__export_source":"insomnia.desktop.app:v7.0.1","resources":[{"_id":"req_f1bbb14af06a4e6d958c712f2b62c239","authentication":{},"body":{},"created":1571070472521,"description":"","headers":[],"isPrivate":false,"metaSortKey":-1571070472521,"method":"GET","modified":1571072469510,"name":"Listagem de usúarios","parameters":[],"parentId":"fld_a795a55426f445e287e5ba77e0ea859f","settingDisableRenderRequestBody":false,"settingEncodeUrl":true,"settingRebuildPath":true,"settingSendCookies":true,"settingStoreCookies":true,"url":"http://localhost:3000/users/1","_type":"request"},{"_id":"fld_a795a55426f445e287e5ba77e0ea859f","created":1571070883181,"description":"","environment":{},"environmentPropertyOrder":null,"metaSortKey":-1571070883181,"modified":1571070883181,"name":"Modulo01","parentId":"wrk_7ee773f7a9234d4c8b1b7f92f98717ce","_type":"request_group"},{"_id":"wrk_7ee773f7a9234d4c8b1b7f92f98717ce","created":1571070439438,"description":"","modified":1571070439438,"name":"Insomnia","parentId":null,"_type":"workspace"},{"_id":"req_9c6a9b281fc14248b90e43ec5b80a993","authentication":{},"body":{},"created":1571070850748,"description":"","headers":[],"isPrivate":false,"metaSortKey":-1571070472471,"method":"GET","modified":1571070889313,"name":"Listagem todos usúarios","parameters":[],"parentId":"fld_a795a55426f445e287e5ba77e0ea859f","settingDisableRenderRequestBody":false,"settingEncodeUrl":true,"settingRebuildPath":true,"settingSendCookies":true,"settingStoreCookies":true,"url":"http://localhost:3000/users/","_type":"request"},{"_id":"req_f5b6dc5de9ea41ca868795ace684a137","authentication":{},"body":{"mimeType":"application/json","text":"{\n\t\"name\": \"Alan Fagner\"\n}"},"created":1571070969291,"description":"","headers":[{"id":"pair_15c3187285074455a34040e538a57c26","name":"Content-Type","value":"application/json"}],"isPrivate":false,"metaSortKey":-1571070472421,"method":"POST","modified":1571072279664,"name":"Criar usúario","parameters":[],"parentId":"fld_a795a55426f445e287e5ba77e0ea859f","settingDisableRenderRequestBody":false,"settingEncodeUrl":true,"settingRebuildPath":true,"settingSendCookies":true,"settingStoreCookies":true,"url":"http://localhost:3000/users","_type":"request"},{"_id":"req_34f27639cad24af093f0d10f67119419","authentication":{},"body":{"mimeType":"application/json","text":"{\n\t\"name\": \"Alan Fagner\"\n}"},"created":1571071323722,"description":"","headers":[{"id":"pair_a4496eee61fc4b36a1e3cc064186cf2a","name":"Content-Type","value":"application/json"}],"isPrivate":false,"metaSortKey":-1571070472371,"method":"PUT","modified":1571072247449,"name":"Editar usúario","parameters":[],"parentId":"fld_a795a55426f445e287e5ba77e0ea859f","settingDisableRenderRequestBody":false,"settingEncodeUrl":true,"settingRebuildPath":true,"settingSendCookies":true,"settingStoreCookies":true,"url":"http://localhost:3000/users/0","_type":"request"},{"_id":"req_b35ef2b15ce7481d8d10aedd27e8210f","authentication":{},"body":{},"created":1571071421429,"description":"","headers":[],"isPrivate":false,"metaSortKey":-1571070472321,"method":"DELETE","modified":1571072490270,"name":"Deletar usúario","parameters":[],"parentId":"fld_a795a55426f445e287e5ba77e0ea859f","settingDisableRenderRequestBody":false,"settingEncodeUrl":true,"settingRebuildPath":true,"settingSendCookies":true,"settingStoreCookies":true,"url":"http://localhost:3000/users/","_type":"request"},{"_id":"env_1916f4a567addd00e0fe16fcbee4012cbdd034a5","color":null,"created":1571070439459,"data":{},"dataPropertyOrder":null,"isPrivate":false,"metaSortKey":1571070439459,"modified":1571070439459,"name":"Base Environment","parentId":"wrk_7ee773f7a9234d4c8b1b7f92f98717ce","_type":"environment"},{"_id":"jar_1916f4a567addd00e0fe16fcbee4012cbdd034a5","cookies":[],"created":1571070439460,"modified":1571070439460,"name":"Default Jar","parentId":"wrk_7ee773f7a9234d4c8b1b7f92f98717ce","_type":"cookie_jar"}]}